simplelayout/__init__.py
simplelayout/__main__.py
simplelayout/cli/__init__.py
simplelayout/cli/cli_generate.py
simplelayout/generator/__init__.py
simplelayout/generator/core.py
simplelayout/generator/utils.py
simplelayout_tang_agui-0.0.3.dist-info/LICENSE.txt
simplelayout_tang_agui-0.0.3.dist-info/METADATA
simplelayout_tang_agui-0.0.3.dist-info/WHEEL
simplelayout_tang_agui-0.0.3.dist-info/entry_points.txt
simplelayout_tang_agui-0.0.3.dist-info/top_level.txt
simplelayout_tang_agui-0.0.3.dist-info/RECORD
