Metadata-Version: 2.1
Name: simplelayout-tang-agui
Version: 0.0.3
Summary: A simplelayout package
Home-page: https://github.com/idrl-assignment/3-simplelayout-package-tang-agui
Author: Tang guijian
Author-email: tangbanllniu@163.com
License: UNKNOWN
Keywords: Simplelayout package
Platform: UNKNOWN
Classifier: Programming Language :: Python :: 3
Classifier: License :: OSI Approved :: MIT License
Classifier: Operating System :: OS Independent
Requires-Python: >=3.6
Requires-Dist: pytest
Requires-Dist: numpy
Requires-Dist: matplotlib
Requires-Dist: scipy
